xbox/nano/__init__.py
xbox/nano/adapters.py
xbox/nano/channel.py
xbox/nano/enum.py
xbox/nano/manager.py
xbox/nano/packer.py
xbox/nano/protocol.py
xbox/nano/xpacker.py
xbox/nano/factory/__init__.py
xbox/nano/factory/audio.py
xbox/nano/factory/channel.py
xbox/nano/factory/control.py
xbox/nano/factory/input.py
xbox/nano/factory/message.py
xbox/nano/factory/video.py
xbox/nano/packet/__init__.py
xbox/nano/packet/audio.py
xbox/nano/packet/control.py
xbox/nano/packet/fec.py
xbox/nano/packet/input.py
xbox/nano/packet/json.py
xbox/nano/packet/message.py
xbox/nano/packet/video.py
xbox/nano/render/__init__.py
xbox/nano/render/codec.py
xbox/nano/render/sink.py
xbox/nano/render/audio/__init__.py
xbox/nano/render/audio/aac.py
xbox/nano/render/audio/sdl.py
xbox/nano/render/client/__init__.py
xbox/nano/render/client/base.py
xbox/nano/render/client/file.py
xbox/nano/render/client/gst.py
xbox/nano/render/client/sdl.py
xbox/nano/render/input/__init__.py
xbox/nano/render/input/base.py
xbox/nano/render/input/controller_db.txt
xbox/nano/render/input/sdl.py
xbox/nano/render/input/sdl_keyboard.py
xbox/nano/render/video/__init__.py
xbox/nano/render/video/sdl.py
xbox/nano/scripts/__init__.py
xbox/nano/scripts/client.py
xbox/nano/scripts/client_mp.py
xbox/nano/scripts/pcap.py
xbox/nano/scripts/replay.py
xbox_smartglass_nano-0.10.1.dist-info/LICENSE
xbox_smartglass_nano-0.10.1.dist-info/METADATA
xbox_smartglass_nano-0.10.1.dist-info/WHEEL
xbox_smartglass_nano-0.10.1.dist-info/entry_points.txt
xbox_smartglass_nano-0.10.1.dist-info/top_level.txt
xbox_smartglass_nano-0.10.1.dist-info/RECORD
