Metadata-Version: 2.1
Name: xbox-smartglass-nano
Version: 0.10.1
Summary: The NANO (v2) part of the xbox smartglass library
Home-page: https://github.com/OpenXbox/xbox-smartglass-nano-python
Author: OpenXbox
Author-email: noreply@openxbox.org
License: MIT
Keywords: xbox one smartglass nano gamestreaming xcloud
Platform: UNKNOWN
Classifier: Development Status :: 4 - Beta
Classifier: Intended Audience :: Developers
Classifier: License :: OSI Approved :: MIT License
Classifier: Topic :: Software Development :: Libraries :: Python Modules
Classifier: Programming Language :: Python :: 3
Classifier: Programming Language :: Python :: 3.7
Classifier: Programming Language :: Python :: 3.8
Classifier: Programming Language :: Python :: 3.9
Requires-Python: >=3.7
Requires-Dist: xbox-smartglass-core (==1.3.0)
Requires-Dist: av (==8.0.3)
Requires-Dist: PySDL2 (==0.9.7)
Provides-Extra: dev
Requires-Dist: pip ; extra == 'dev'
Requires-Dist: bump2version ; extra == 'dev'
Requires-Dist: wheel ; extra == 'dev'
Requires-Dist: watchdog ; extra == 'dev'
Requires-Dist: flake8 ; extra == 'dev'
Requires-Dist: coverage ; extra == 'dev'
Requires-Dist: Sphinx ; extra == 'dev'
Requires-Dist: sphinx-rtd-theme ; extra == 'dev'
Requires-Dist: recommonmark ; extra == 'dev'
Requires-Dist: twine ; extra == 'dev'
Requires-Dist: pytest ; extra == 'dev'
Requires-Dist: pytest-asyncio ; extra == 'dev'
Requires-Dist: pytest-console-scripts ; extra == 'dev'
Requires-Dist: pytest-runner ; extra == 'dev'
